jsonproject/__main__.py
jsonproject-0.1.1.dist-info/METADATA
jsonproject-0.1.1.dist-info/WHEEL
jsonproject-0.1.1.dist-info/top_level.txt
jsonproject-0.1.1.dist-info/RECORD
