Metadata-Version: 2.1
Name: jsonproject
Version: 0.1.1
Summary: Easily manage your projects with JSON files
Home-page: https://github.com/Proactive-Development/jsonproject/
Author: Proactive Development
License: NONE
Platform: UNKNOWN
